Metadata-Version: 2.1
Name: evotree
Version: 0.0.0.2
Summary: Python package and CLI for processing phylogenetic tree
Home-page: http://github.com/heche-psb/evotree
Author: Hengchi Chen
Author-email: heche@psb.vib-ugent.be
License: GPL
License-File: LICENSE
Requires-Dist: biopython>=1.76
Requires-Dist: click>=7.1.2
Requires-Dist: pandas>=1.4.4
Requires-Dist: numpy>=1.19.0
Requires-Dist: rich>=12.5.1
Requires-Dist: matplotlib>=3.2.2
Requires-Dist: scipy>=1.10.1
Requires-Dist: statsmodels>=0.14.1
Requires-Dist: tqdm>=4.64.1
Requires-Dist: pymc>=5.6.1
Requires-Dist: arviz>=0.15.1
Requires-Dist: pytensor>=2.12.3
